<?xml version="1.0" encoding="utf-8" ?>

<!--
    This file is part of extra500

    The extra500 is free software: you can redistribute it and/or modify
    it under the terms of the GNU General Public License as published by
    the Free Software Foundation, either version 2 of the License, or
    (at your option) any later version.

    The extra500 is distributed in the hope that it will be useful,
    but WITHOUT ANY WARRANTY; without even the implied warranty of
    MERCHANTABILITY or FITNESS FOR A PARTICULAR PURPOSE.  See the
    GNU General Public License for more details.

    You should have received a copy of the GNU General Public License
    along with extra500.  If not, see <http://www.gnu.org/licenses/>.

      Authors: Dirk Dittmann, Eric van den Berg, Thomas Grossberger 
      Date: March 13 2013

      Last change:      Eric van den Berg
      Date:             01.10.17
-->
<PropertyList>

<!--path>MasterPanel.ac
only for submodels</path-->



<!-- Submodels -->

<!-- switches -->

<model>
  <name>overspeed switch</name>
  <path>Aircraft/extra500/Models/panels/overspeed.xml</path>
	<offsets>
		<x-m>0.007</x-m>
		<y-m>0.01250</y-m>	
		<z-m>-0.002002</z-m>
		<roll-deg>0</roll-deg>
		<pitch-deg>90</pitch-deg>
		<yaw-deg>0</yaw-deg>
	</offsets>
</model>

</PropertyList>
